{
  "template": "SNB_AHLY",
  "confidence": "HIGH",
  "amount": 4000.0,
  "currency": null,
  "transaction_id": "20251104115613790",
  "date": "2025/11/04",
  "sender": "11100331685503",
  "sender_name": "KHULOD ABDELKHALEG ABDELRAHIM ELHAG",
  "receiver": "01400015243104",
  "receiver_name": "وكالة جرر الكناري pull و السياحه",
  "iban": null,
  "status": null,
  "transaction_type": null,
  "comment": null,
  "raw_text": "--- PSM 4 ---\nنه\nالأهلى ‎SNB‏\n‏إيصال\n\nإيصال عملية تحويل إلى مستفيد ‎ola‏ الينك الأهلي\nأعد ل ‎KHULOD ABDELKHALEG ABDELRAHIM ELHAG‏ بتاريخ 2025/11/04 ووقت 19:52:37\n\nعزيزي العميل,\n\nرقم المرجع 20251104115613790\nالرجاء الاحتفاط به للاستخدام في المستقيل\n\nالرقم الضريبي 300002471110003\n\nتنشكرك لإستخدام خدمة الأهلي مويايل.\n\nالقرع\nالعملة 2\n\nرقع الحساب 11100331685503\nالمبلع 00000\n\nالرسوم محاني\n\nضرييه القيعة العضاكة مجاني\n\nالمبلع الإحمالي 34,000.00\n\n04/11/2025\n#\n01400015243104\n\nوكالة جرر الكناري للسفر و السياحه\n#4,000.00\n\nرأس الحال 60.000,000,000 ‎Jb,‏ سعودي مدقوع بالكاعل\n\n4030001588 ‏نعاري رقم‎ Jaw\n\nخاضعة لإشرافى ورقاية البنك المركزي السعودي\n\n\n--- PSM 3 ---\nنه\nالأهلى ‎SNB‏\n\nإيصال عملية تحويل إلى مستفيد ‎ola‏ الينك الأهلي\nأعد ل ‎KHULOD ABDELKHALEG ABDELRAHIM ELHAG‏ بتاريخ 2025/11/04 ووقت 19:52:37\n\nعزيزي العميل,\n\nرقم المرجع 20251104115613790\nالرجاء الاحتفاط به للاستخدام في المستقيل\n\nالرقم الضريبي 300002471110003\n\nتنشكرك لإستخدام خدمة الأهلي مويايل.\n\nالقرع\nالعملة 2\n\nرقع الحساب 11100331685503\nالمبلع 00000\n\nالرسوم محاني\n\nضرييه القيعة العضاكة مجاني\n\nالمبلع الإحمالي 34,000.00\n\n04/11/2025\n\n2\n\n2 2 94\n\nوكالة جرر الكناري ‎paul!‏ و السياحة\n#4,000.00\n\nرأس الحال 60.000,000,000 ‎Jb,‏ سعودي مدقوع بالكاعل\n\n4030001588 ‏نعاري رقم‎ Jaw\n\nخاضعة لإشرافى ورقاية البنك المركزي السعودي\n\n\n--- PSM 6 ---\nنه\nالأهلى ‎SNB‏\n‏إيصال\n‏إيصال عملية تحويل إلى مستقيد داخل ‎lil]‏ الأهلي\nأعد ل ‎KHULOD ABDELKHALEG ABDELRAHIM ELHAG‏ بتاريخ 2025/11/04 ووقت 19:52:37\nعزيزي العميل,\nرقم المرجع 20251104115613790\nالرجاء الاحتماط به للاستخدام في المسنقيل\nالرقم الضريبي 300002471110003\nتنشكرك لإستخدام خدمة الأهلي مويايل.\nالفرع\nالعملة 2\nرفم الحساب 11100331685503\nالمبلع 44,000.00\nالرسوم محاني\nضرييه القيعة العضاكة مجاني\n‎glial!‏ الإحمالي 2.60 اد\nإلى\nناريح التتغيذ 04/11/2025\nالعجلة ع2\nرقم الحساب 4 ش22\nالمستفيد وكالة جرر الكناري ‎pull‏ و السياحه\nميلع الإيداع #4,000.00\nملاحظات\nالببك الأهتي السمودي\nشركه مساهمة سعودية\nرأس الحال 60.000,000,000 ربال سعودي مدقوع بالكاعل\n‎Jaw‏ نعاري رقم 4030001588\nخاضعة لإشرافى ورقاية البنك المركزي السعودي\n\n--- PSM 11 ---\nSNB ‏الأهلي‎\n\nإيصال\n\nإيصال عملية تحويل إلى مستقيد ‎slo‏ الينك الأهلي\n\n19:52:37 ‏بتاريخ 2025/11/04 ووقت‎ KHULOD ABDELKHALEG ABDELRAHIM ELHAG ‏أعد ل‎\n\nعزيزي العميل,\n\nرقم المرجع\n\n20251104115613790\n\nالرجاء الاحتفاط به تلاستخدام في المسنقيل\n\nالرقم الضريبي 300002471110003\n\nتنشكرك لإستخدام خدمة الأهلي مويايل.\n\nالفرع\n\nالعملة\n\n=\n\n2\n\n11100331685503\n\nالمبلع\n\n44,000.00\n\nالرسوم\n\nمحاني\n\nضرييه القيعة العضاكة\n\nعجاني\n\nالمبلع الإحمالي\n\n44,000.00\n\nناريح التتغبذ\n\n04/11/2025\n\nالعجلة\n\nع2\n\nرقم الحساب\n\n01400015243104\n\nالمستفيد\n\nوكالة جرر الكناري للسفر و السياحه\n\nعبلع الإيداع\n\n#4,000.00\n\nملاحظات\n\nالببك الأهتي السمودي\n\nركه مساهمة سعودية\n\nرأس المال 60.000,000,000 ريال سعودي مدقوع بالكاعل\n\nسحل نحاري رقم 4030001588\n\nخاضعة لإشرافى ورقاية البنك المركزي السعودي\n",
  "evidence": {
    "transaction_id": "المرجع 20251104115613790",
    "date": "2025/11/04",
    "sender_name": "أعد ل KHULOD ABDELKHALEG ABDELRAHIM ELHAG بتاريخ",
    "sender": "القرع\nالعملة 2\nرقع الحساب 11100331685503",
    "receiver": "ناريح التتغبذ\n04/11/2025\nالعجلة\nع2\nرقم الحساب\n01400015243104",
    "receiver_name": "المستفيد وكالة جرر الكناري pull و السياحه",
    "amount_template": "ميلع الإيداع #4,000.00"
  }
}